jkq/qmap/__init__.py
jkq/qmap/compile.py
jkq/qmap/pyqmap.cp38-win_amd64.pyd
jkq.qmap-1.5.1.dist-info/LICENSE
jkq.qmap-1.5.1.dist-info/METADATA
jkq.qmap-1.5.1.dist-info/WHEEL
jkq.qmap-1.5.1.dist-info/top_level.txt
jkq.qmap-1.5.1.dist-info/RECORD
