Metadata-Version: 2.1
Name: jkq.qmap
Version: 1.5.1
Summary: QMAP - A JKQ tool for Quantum Circuit Mapping
Home-page: https://iic.jku.at/eda/research/ibm_qx_mapping/
Author: Lukas Burgholzer
Author-email: lukas.burgholzer@jku.at
License: MIT
Project-URL: Source, https://github.com/iic-jku/qmap/
Project-URL: Tracker, https://github.com/iic-jku/qmap/issues
Project-URL: Research, https://iic.jku.at/eda/research/ibm_qx_mapping/
Keywords: jkq quantum compilation mapping
Platform: UNKNOWN
Classifier: Development Status :: 5 - Production/Stable
Classifier: Programming Language :: Python :: 3
Classifier: Programming Language :: C++
Classifier: License :: OSI Approved :: MIT License
Classifier: Operating System :: Microsoft :: Windows
Classifier: Operating System :: MacOS
Classifier: Operating System :: POSIX :: Linux
Classifier: Intended Audience :: Science/Research
Classifier: Natural Language :: English
Classifier: Topic :: Scientific/Engineering :: Electronic Design Automation (EDA)
License-File: LICENSE
